setup.py
singleton_factory/__init__.py
singleton_factory.egg-info/PKG-INFO
singleton_factory.egg-info/SOURCES.txt
singleton_factory.egg-info/dependency_links.txt
singleton_factory.egg-info/top_level.txt